Metadata-Version: 1.1
Name: migrate
Version: 0.3.6
Summary: 
